libquantum/__init__.py
libquantum/atoms.py
libquantum/atoms_inverse.py
libquantum/blast_pulse.py
libquantum/doppler.py
libquantum/dyadics.py
libquantum/entropy.py
libquantum/export.py
libquantum/gabor_box.py
libquantum/rms_envelope.py
libquantum/scales.py
libquantum/spectra.py
libquantum/stockwell_orig.py
libquantum/styx_cwt.py
libquantum/styx_fft.py
libquantum/styx_stx.py
libquantum/styx_stx_loopy.py
libquantum/synthetics.py
libquantum/tfr_gate_pick.py
libquantum/utils.py
libquantum/plot_templates/__init__.py
libquantum/plot_templates/plot_geo_scatter_2d_3d.py
libquantum/plot_templates/plot_time_frequency_picks.py
libquantum/plot_templates/plot_time_frequency_reps.py
libquantum/plot_templates/plot_time_frequency_reps_black.py
libquantum2/__init__.py
libquantum2/benchmark_signals.py
libquantum-1.5.23.dist-info/LICENSE
libquantum-1.5.23.dist-info/METADATA
libquantum-1.5.23.dist-info/WHEEL
libquantum-1.5.23.dist-info/top_level.txt
libquantum-1.5.23.dist-info/RECORD
