Metadata-Version: 2.1
Name: libquantum
Version: 1.5.23
Summary: Library for implementing standardized time-frequency representations.
Author-email: "RedVox, Inc" <support@redvox.io>
License: 
Project-URL: homepage, https://github.com/RedVoxInc/libquantum
Project-URL: PyPI, https://pypi.org/project/libquantum/
Requires-Python: <3.11,>=3.8
License-File: LICENSE
Requires-Dist: librosa ==0.10.2
Requires-Dist: libwwz ==1.3.3
Requires-Dist: matplotlib ==3.9.1
Requires-Dist: numpy ==1.26.4
Requires-Dist: pandas ==2.2.2
Requires-Dist: redvox ==3.8.6
